lmnt/__init__.py
lmnt/_base_client.py
lmnt/_client.py
lmnt/_compat.py
lmnt/_constants.py
lmnt/_exceptions.py
lmnt/_files.py
lmnt/_models.py
lmnt/_qs.py
lmnt/_resource.py
lmnt/_response.py
lmnt/_streaming.py
lmnt/_types.py
lmnt/_version.py
lmnt/py.typed
lmnt/_utils/__init__.py
lmnt/_utils/_compat.py
lmnt/_utils/_datetime_parse.py
lmnt/_utils/_logs.py
lmnt/_utils/_proxy.py
lmnt/_utils/_reflection.py
lmnt/_utils/_resources_proxy.py
lmnt/_utils/_streams.py
lmnt/_utils/_sync.py
lmnt/_utils/_transform.py
lmnt/_utils/_typing.py
lmnt/_utils/_utils.py
lmnt/lib/.keep
lmnt/lib/__init__.py
lmnt/lib/websocket_streaming.py
lmnt/resources/__init__.py
lmnt/resources/accounts.py
lmnt/resources/sessions.py
lmnt/resources/speech.py
lmnt/resources/voices.py
lmnt/types/__init__.py
lmnt/types/account_retrieve_response.py
lmnt/types/speech_convert_params.py
lmnt/types/speech_generate_detailed_params.py
lmnt/types/speech_generate_detailed_response.py
lmnt/types/speech_generate_params.py
lmnt/types/voice.py
lmnt/types/voice_create_params.py
lmnt/types/voice_delete_response.py
lmnt/types/voice_list_params.py
lmnt/types/voice_list_response.py
lmnt/types/voice_update_params.py
lmnt/types/voice_update_response.py
lmnt-2.4.0.dist-info/METADATA
lmnt-2.4.0.dist-info/WHEEL
lmnt-2.4.0.dist-info/licenses/LICENSE
lmnt-2.4.0.dist-info/RECORD
